IpfsEthereumYitaiFangRumenJingdianJiaocheng/README.md
IpfsEthereumYitaiFangRumenJingdianJiaocheng/__init__.py
IpfsEthereumYitaiFangRumenJingdianJiaocheng/__main__.py
IpfsEthereumYitaiFangRumenJingdianJiaocheng/file.epub
IpfsEthereumYitaiFangRumenJingdianJiaocheng/index.html
IpfsEthereumYitaiFangRumenJingdianJiaocheng/css/__init__.py
IpfsEthereumYitaiFangRumenJingdianJiaocheng/css/annotations.css
IpfsEthereumYitaiFangRumenJingdianJiaocheng/css/main.css
IpfsEthereumYitaiFangRumenJingdianJiaocheng/css/normalize.css
IpfsEthereumYitaiFangRumenJingdianJiaocheng/css/popup.css
IpfsEthereumYitaiFangRumenJingdianJiaocheng/font/__init__.py
IpfsEthereumYitaiFangRumenJingdianJiaocheng/font/fontello.eot
IpfsEthereumYitaiFangRumenJingdianJiaocheng/font/fontello.svg
IpfsEthereumYitaiFangRumenJingdianJiaocheng/font/fontello.ttf
IpfsEthereumYitaiFangRumenJingdianJiaocheng/font/fontello.woff
IpfsEthereumYitaiFangRumenJingdianJiaocheng/img/__init__.py
IpfsEthereumYitaiFangRumenJingdianJiaocheng/img/annotator-glyph-sprite.png
IpfsEthereumYitaiFangRumenJingdianJiaocheng/img/annotator-icon-sprite.png
IpfsEthereumYitaiFangRumenJingdianJiaocheng/img/apple-touch-icon.png
IpfsEthereumYitaiFangRumenJingdianJiaocheng/img/cancelfullscreen.png
IpfsEthereumYitaiFangRumenJingdianJiaocheng/img/close.png
IpfsEthereumYitaiFangRumenJingdianJiaocheng/img/fullscreen.png
IpfsEthereumYitaiFangRumenJingdianJiaocheng/img/loader.gif
IpfsEthereumYitaiFangRumenJingdianJiaocheng/img/menu-icon.png
IpfsEthereumYitaiFangRumenJingdianJiaocheng/img/save.png
IpfsEthereumYitaiFangRumenJingdianJiaocheng/img/saved.png
IpfsEthereumYitaiFangRumenJingdianJiaocheng/img/settings-s.png
IpfsEthereumYitaiFangRumenJingdianJiaocheng/img/settings.png
IpfsEthereumYitaiFangRumenJingdianJiaocheng/img/star.png
IpfsEthereumYitaiFangRumenJingdianJiaocheng/js/__init__.py
IpfsEthereumYitaiFangRumenJingdianJiaocheng/js/epub.js
IpfsEthereumYitaiFangRumenJingdianJiaocheng/js/epub.min.js
ipfs_ethereum_yitai_fang_rumen_jingdian_jiaocheng-2024.3.5.0.dist-info/METADATA
ipfs_ethereum_yitai_fang_rumen_jingdian_jiaocheng-2024.3.5.0.dist-info/WHEEL
ipfs_ethereum_yitai_fang_rumen_jingdian_jiaocheng-2024.3.5.0.dist-info/entry_points.txt
ipfs_ethereum_yitai_fang_rumen_jingdian_jiaocheng-2024.3.5.0.dist-info/top_level.txt
ipfs_ethereum_yitai_fang_rumen_jingdian_jiaocheng-2024.3.5.0.dist-info/RECORD
